mgoat/__init__.py
mgoat/cli.py
mgoat/client.py
mgoat/models.py
mgoat/strategies.py
mgoat-0.1.0.dist-info/METADATA
mgoat-0.1.0.dist-info/WHEEL
mgoat-0.1.0.dist-info/entry_points.txt
mgoat-0.1.0.dist-info/licenses/LICENSE
mgoat-0.1.0.dist-info/RECORD
