Metadata-Version: 2.4
Name: mgoat
Version: 0.1.0
Summary: The Rust-Powered LLM Red Teaming Framework - Python Wrapper
Project-URL: Homepage, https://github.com/relaxcloud-cn/mgoat
Project-URL: Documentation, https://github.com/relaxcloud-cn/mgoat#readme
Project-URL: Repository, https://github.com/relaxcloud-cn/mgoat-py
Project-URL: Issues, https://github.com/relaxcloud-cn/mgoat-py/issues
Author-email: MGoat Contributors <mgoat@relaxcloud.cn>
License-Expression: MIT
License-File: LICENSE
Keywords: ai-safety,jailbreak,llm,red-team,security,testing
Classifier: Development Status :: 4 - Beta
Classifier: Intended Audience :: Developers
Classifier: Intended Audience :: Science/Research
Classifier: License :: OSI Approved :: MIT License
Classifier: Operating System :: OS Independent
Classifier: Programming Language :: Python :: 3
Classifier: Programming Language :: Python :: 3.8
Classifier: Programming Language :: Python :: 3.9
Classifier: Programming Language :: Python :: 3.10
Classifier: Programming Language :: Python :: 3.11
Classifier: Programming Language :: Python :: 3.12
Classifier: Topic :: Scientific/Engineering :: Artificial Intelligence
Classifier: Topic :: Security
Requires-Python: >=3.8
Requires-Dist: httpx>=0.24.0
Requires-Dist: pydantic>=2.0.0
Requires-Dist: rich>=13.0.0
Requires-Dist: typer>=0.9.0
Provides-Extra: dev
Requires-Dist: black>=23.0.0; extra == 'dev'
Requires-Dist: mypy>=1.0.0; extra == 'dev'
Requires-Dist: pytest-asyncio>=0.21.0; extra == 'dev'
Requires-Dist: pytest-cov>=4.0.0; extra == 'dev'
Requires-Dist: pytest>=7.0.0; extra == 'dev'
Requires-Dist: ruff>=0.1.0; extra == 'dev'
